anchor/__init__.py
anchor/__main__.py
anchor/ast.py
anchor/builtins.py
anchor/compile.py
anchor/factory.py
anchor/keyword.py
anchor/lex.py
anchor/parse.py
anchor/symtable.py
anchor/system.py
anchor/token.py
anchor/ply/__init__.py
anchor/ply/lex.py
anchor/ply/yacc.py
anpl-0.0.7.dist-info/LICENSE
anpl-0.0.7.dist-info/METADATA
anpl-0.0.7.dist-info/WHEEL
anpl-0.0.7.dist-info/entry_points.txt
anpl-0.0.7.dist-info/top_level.txt
anpl-0.0.7.dist-info/RECORD
