Metadata-Version: 2.1
Name: anpl
Version: 0.0.7
Summary: Anchor Programming Language
Home-page: https://github.com/luojiahai/anchor
Author: luojiahai
Author-email: luo@jiahai.co
License: UNKNOWN
Project-URL: Bug Tracker, https://github.com/luojiahai/anchor/issues
Platform: UNKNOWN
Classifier: Programming Language :: Python :: 3.9
Classifier: License :: OSI Approved :: MIT License
Classifier: Operating System :: OS Independent
Requires-Python: >=3.9
License-File: LICENSE
